Workbook

Sheet Read_Me
A1: ReportDesk - Institutional Client Report Pack (September 2026)
A2: Synthetic data for a portfolio project. Clients, securities and values are invented. All values in USD.
A4: How it works
A5: 1. SQL in PostgreSQL values every holding, runs 8 data-quality checks and calculates returns vs benchmark.
A6: 2. Query results are exported to CSV and pasted into the grey Data_ sheets (keep the headers in row 1).
A7: 3. The Report sheet builds one client's report. Change the client ID in Settings!B2 to switch client.
A8: 4. The GenerateClientReports macro creates a PDF for every READY client and skips BLOCKED ones, logging each.
A10: Rule: a client with any BLOCKER in Data_DQ must not receive a report until the issue is fixed.
A11: Data_TopHoldings column G (Key) is a helper formula: extend it down if you paste more rows.

Sheet Report
B1: Monthly Portfolio Report
B2: ="Period ending "&TEXT(Settings!B1,"dd mmmm yyyy")&" | All values in USD" -> Period ending 30 September 2026 | All values in USD
B4: Client | C4: =INDEX(Data_Summary!$B:$B,MATCH(Settings!$B$2,Data_Summary!$A:$A,0)) -> Kingsbridge Pension Scheme
B5: Client type | C5: =INDEX(Data_Summary!$C:$C,MATCH(Settings!$B$2,Data_Summary!$A:$A,0)) -> Pension Fund
B6: Country | C6: =INDEX(Data_Summary!$D:$D,MATCH(Settings!$B$2,Data_Summary!$A:$A,0)) -> United Kingdom
B7: Benchmark | C7: =INDEX(Data_Summary!$E:$E,MATCH(Settings!$B$2,Data_Summary!$A:$A,0)) -> 60/40 Global Balanced Index
B9: Portfolio value | F9: Performance (month)
B10: Opening value (31 Aug) | C10: =INDEX(Data_Summary!$F:$F,MATCH(Settings!$B$2,Data_Summary!$A:$A,0)) -> 172783514 | F10: Portfolio return | G10: =INDEX(Data_Summary!$J:$J,MATCH(Settings!$B$2,Data_Summary!$A:$A,0)) -> 0.001837
B11: Net contributions / (withdrawals) | C11: =INDEX(Data_Summary!$H:$H,MATCH(Settings!$B$2,Data_Summary!$A:$A,0)) -> 2900000 | F11: Benchmark return | G11: =INDEX(Data_Summary!$K:$K,MATCH(Settings!$B$2,Data_Summary!$A:$A,0)) -> 0.0094
B12: Investment gain / (loss) | C12: =INDEX(Data_Summary!$I:$I,MATCH(Settings!$B$2,Data_Summary!$A:$A,0)) -> 320124 | F12: Relative (bps) | G12: =INDEX(Data_Summary!$L:$L,MATCH(Settings!$B$2,Data_Summary!$A:$A,0)) -> -75.6
B13: Closing value (30 Sep) | C13: =INDEX(Data_Summary!$G:$G,MATCH(Settings!$B$2,Data_Summary!$A:$A,0)) -> 176003638
B14: Check: opening + flows + gain - closing | C14: =C10+C11+C12-C13 -> 0
B16: Asset allocation (30 Sep)
B17: Asset class | C17: Market value | D17: Weight
B18: Equity | C18: =SUMIFS(Data_Allocation!$C:$C,Data_Allocation!$A:$A,Settings!$B$2,Data_Allocation!$B:$B,B18) -> 121359120 | D18: =SUMIFS(Data_Allocation!$D:$D,Data_Allocation!$A:$A,Settings!$B$2,Data_Allocation!$B:$B,B18) -> 0.689526
B19: Fixed Income | C19: =SUMIFS(Data_Allocation!$C:$C,Data_Allocation!$A:$A,Settings!$B$2,Data_Allocation!$B:$B,B19) -> 47074518 | D19: =SUMIFS(Data_Allocation!$D:$D,Data_Allocation!$A:$A,Settings!$B$2,Data_Allocation!$B:$B,B19) -> 0.267463
B20: Cash | C20: =SUMIFS(Data_Allocation!$C:$C,Data_Allocation!$A:$A,Settings!$B$2,Data_Allocation!$B:$B,B20) -> 7570000 | D20: =SUMIFS(Data_Allocation!$D:$D,Data_Allocation!$A:$A,Settings!$B$2,Data_Allocation!$B:$B,B20) -> 0.04301
B21: Total | C21: =SUM(C18:C20) -> 176003638 | D21: =SUM(D18:D20) -> 0.999999
B27: Top 5 holdings (excluding cash)
B28: Security | C28: Asset class | D28: Weight | F28: Market value
B29: =IFERROR(INDEX(Data_TopHoldings!$C:$C,MATCH(Settings!$B$2&"-"&1,Data_TopHoldings!$G:$G,0)),"") -> Cedar Rail Holdings | C29: =IFERROR(INDEX(Data_TopHoldings!$D:$D,MATCH(Settings!$B$2&"-"&1,Data_TopHoldings!$G:$G,0)),"") -> Equity | D29: =IFERROR(INDEX(Data_TopHoldings!$F:$F,MATCH(Settings!$B$2&"-"&1,Data_TopHoldings!$G:$G,0)),"") -> 0.279992 | F29: =IFERROR(INDEX(Data_TopHoldings!$E:$E,MATCH(Settings!$B$2&"-"&1,Data_TopHoldings!$G:$G,0)),"") -> 49279560
B30: =IFERROR(INDEX(Data_TopHoldings!$C:$C,MATCH(Settings!$B$2&"-"&2,Data_TopHoldings!$G:$G,0)),"") -> Lumen Consumer Brands | C30: =IFERROR(INDEX(Data_TopHoldings!$D:$D,MATCH(Settings!$B$2&"-"&2,Data_TopHoldings!$G:$G,0)),"") -> Equity | D30: =IFERROR(INDEX(Data_TopHoldings!$F:$F,MATCH(Settings!$B$2&"-"&2,Data_TopHoldings!$G:$G,0)),"") -> 0.1427 | F30: =IFERROR(INDEX(Data_TopHoldings!$E:$E,MATCH(Settings!$B$2&"-"&2,Data_TopHoldings!$G:$G,0)),"") -> 25115670
B31: =IFERROR(INDEX(Data_TopHoldings!$C:$C,MATCH(Settings!$B$2&"-"&3,Data_TopHoldings!$G:$G,0)),"") -> UK Gilt 4.00% 2030 | C31: =IFERROR(INDEX(Data_TopHoldings!$D:$D,MATCH(Settings!$B$2&"-"&3,Data_TopHoldings!$G:$G,0)),"") -> Fixed Income | D31: =IFERROR(INDEX(Data_TopHoldings!$F:$F,MATCH(Settings!$B$2&"-"&3,Data_TopHoldings!$G:$G,0)),"") -> 0.100462 | F31: =IFERROR(INDEX(Data_TopHoldings!$E:$E,MATCH(Settings!$B$2&"-"&3,Data_TopHoldings!$G:$G,0)),"") -> 17681718
B32: =IFERROR(INDEX(Data_TopHoldings!$C:$C,MATCH(Settings!$B$2&"-"&4,Data_TopHoldings!$G:$G,0)),"") -> Orchid Pharmaceuticals | C32: =IFERROR(INDEX(Data_TopHoldings!$D:$D,MATCH(Settings!$B$2&"-"&4,Data_TopHoldings!$G:$G,0)),"") -> Equity | D32: =IFERROR(INDEX(Data_TopHoldings!$F:$F,MATCH(Settings!$B$2&"-"&4,Data_TopHoldings!$G:$G,0)),"") -> 0.087157 | F32: =IFERROR(INDEX(Data_TopHoldings!$E:$E,MATCH(Settings!$B$2&"-"&4,Data_TopHoldings!$G:$G,0)),"") -> 15339955
B33: =IFERROR(INDEX(Data_TopHoldings!$C:$C,MATCH(Settings!$B$2&"-"&5,Data_TopHoldings!$G:$G,0)),"") -> Atlas Mining 6.00% 2030 | C33: =IFERROR(INDEX(Data_TopHoldings!$D:$D,MATCH(Settings!$B$2&"-"&5,Data_TopHoldings!$G:$G,0)),"") -> Fixed Income | D33: =IFERROR(INDEX(Data_TopHoldings!$F:$F,MATCH(Settings!$B$2&"-"&5,Data_TopHoldings!$G:$G,0)),"") -> 0.074486 | F33: =IFERROR(INDEX(Data_TopHoldings!$E:$E,MATCH(Settings!$B$2&"-"&5,Data_TopHoldings!$G:$G,0)),"") -> 13109825
B35: Data status | C35: =INDEX(Data_Summary!$M:$M,MATCH(Settings!$B$2,Data_Summary!$A:$A,0)) -> READY - CHECK WARNINGS
B36: Values use month-end prices. Return = simple Dietz: (closing - opening - net flows) / (opening + 0.5 x net flows). Past performance is not a guide to future returns.

Sheet Report_Log
A1: Generated At | B1: Client ID | C1: Client Name | D1: Data Status | E1: Result | F1: File

Sheet Settings
A1: Report month-end | B1: 46295 | C1: Reporting period end
A2: Selected client ID | B2: C01 | C2: Type C01 to C06 to preview a client's report (the macro changes this automatically)

Sheet Data_Summary
A1: client_id | B1: client_name | C1: client_type | D1: country | E1: benchmark_name | F1: bmv | G1: emv | H1: net_flows | I1: investment_gain | J1: portfolio_return | K1: benchmark_return | L1: excess_bps | M1: report_status
A2: C01 | B2: Kingsbridge Pension Scheme | C2: Pension Fund | D2: United Kingdom | E2: 60/40 Global Balanced Index | F2: 172783514 | G2: 176003638 | H2: 2900000 | I2: 320124 | J2: 0.001837 | K2: 0.0094 | L2: -75.6 | M2: READY - CHECK WARNINGS
A3: C02 | B3: Rheinfeld Insurance AG | C3: Insurance | D3: Germany | E3: Global Aggregate Bond Index | F3: 190224832 | G3: 189754489 | H3: -800000 | I3: 329657 | J3: 0.001737 | K3: -0.0042 | L3: 59.4 | M3: READY - CHECK WARNINGS
A4: C03 | B4: Amsterhaven Foundation | C4: Foundation | D4: Netherlands | E4: Global Equity Index | F4: 274733417 | G4: 273920432 | H4: 0 | I4: -812985 | J4: -0.002959 | K4: 0.0185 | L4: -214.6 | M4: READY - CHECK WARNINGS
A5: C04 | B5: Al Noor Reserve Fund | C5: Sovereign Wealth Fund | D5: United Arab Emirates | E5: 60/40 Global Balanced Index | F5: 272801857 | G5: 219684436 | H5: -2550000 | I5: -50567421 | J5: -0.186234 | K5: 0.0094 | L5: -1956.3 | M5: BLOCKED
A6: C05 | B6: Table Bay Retirement Fund | C6: Pension Fund | D6: South Africa | E6: Global Equity Index | F6: 265133992 | G6: 263222259 | H6: 400000 | I6: -2311733 | J6: -0.008713 | K6: 0.0185 | L6: -272.1 | M6: BLOCKED
A7: C06 | B7: Fjordline Mutual Pension | C7: Pension Fund | D7: Sweden | E7: 60/40 Global Balanced Index | F7: 302759239 | G7: 310421063 | H7: -1450000 | I7: 9111824 | J7: 0.030168 | K7: 0.0094 | L7: 207.7 | M7: BLOCKED

Sheet Data_Allocation
A1: client_id | B1: asset_class | C1: market_value | D1: weight
A2: C01 | B2: Cash | C2: 7570000 | D2: 0.04301
A3: C01 | B3: Equity | C3: 121359120 | D3: 0.689526
A4: C01 | B4: Fixed Income | C4: 47074518 | D4: 0.267463
A5: C02 | B5: Cash | C5: 1970000 | D5: 0.010382
A6: C02 | B6: Equity | C6: 28978920 | D6: 0.152718
A7: C02 | B7: Fixed Income | C7: 158805569 | D7: 0.8369
A8: C03 | B8: Cash | C8: 3510000 | D8: 0.012814
A9: C03 | B9: Equity | C9: 248043895 | D9: 0.905533
A10: C03 | B10: Fixed Income | C10: 22366537 | D10: 0.081653
A11: C04 | B11: Cash | C11: 2320000 | D11: 0.010561
A12: C04 | B12: Equity | C12: 145314025 | D12: 0.661467
A13: C04 | B13: Fixed Income | C13: 72050411 | D13: 0.327972
... A19: C06 | B19: Fixed Income | C19: 111581993 | D19: 0.359454

Sheet Data_TopHoldings
A1: client_id | B1: rank_no | C1: security_name | D1: asset_class | E1: market_value | F1: weight | G1: key
A2: C01 | B2: 1 | C2: Cedar Rail Holdings | D2: Equity | E2: 49279560 | F2: 0.279992 | G2: =A2&"-"&B2 -> C01-1
A3: C01 | B3: 2 | C3: Lumen Consumer Brands | D3: Equity | E3: 25115670 | F3: 0.1427 | G3: =A3&"-"&B3 -> C01-2
A4: C01 | B4: 3 | C4: UK Gilt 4.00% 2030 | D4: Fixed Income | E4: 17681718 | F4: 0.100462 | G4: =A4&"-"&B4 -> C01-3
A5: C01 | B5: 4 | C5: Orchid Pharmaceuticals | D5: Equity | E5: 15339955 | F5: 0.087157 | G5: =A5&"-"&B5 -> C01-4
A6: C01 | B6: 5 | C6: Atlas Mining 6.00% 2030 | D6: Fixed Income | E6: 13109825 | F6: 0.074486 | G6: =A6&"-"&B6 -> C01-5
A7: C02 | B7: 1 | C7: Harbourline Bank 5.10% 2029 | D7: Fixed Income | E7: 39680592 | F7: 0.209115 | G7: =A7&"-"&B7 -> C02-1
A8: C02 | B8: 2 | C8: German Bund 2.50% 2033 | D8: Fixed Income | E8: 36003960 | F8: 0.18974 | G8: =A8&"-"&B8 -> C02-2
A9: C02 | B9: 3 | C9: Japan JGB 1.10% 2034 | D9: Fixed Income | E9: 22466620 | F9: 0.118398 | G9: =A9&"-"&B9 -> C02-3
A10: C02 | B10: 4 | C10: UK Gilt 4.00% 2030 | D10: Fixed Income | E10: 21674364 | F10: 0.114223 | G10: =A10&"-"&B10 -> C02-4
A11: C02 | B11: 5 | C11: Northwind Technologies | D11: Equity | E11: 16464420 | F11: 0.086767 | G11: =A11&"-"&B11 -> C02-5
A12: C03 | B12: 1 | C12: Atlas Mining Corp | D12: Equity | E12: 82824020 | F12: 0.302365 | G12: =A12&"-"&B12 -> C03-1
A13: C03 | B13: 2 | C13: Lumen Consumer Brands | D13: Equity | E13: 52096365 | F13: 0.190188 | G13: =A13&"-"&B13 -> C03-2
... A31: C06 | B31: 5 | C31: Atlas Mining Corp | D31: Equity | E31: 22315280 | F31: 0.071887 | G31: =A31&"-"&B31 -> C06-5

Sheet Data_DQ
A1: client_id | B1: check_name | C1: severity | D1: security_id | E1: detail
A2: C04 | B2: Missing month-end price | C2: BLOCKER | D2: EQ002 | E2: No price on 2026-09-30
A3: C05 | B3: Cash does not reconcile | C3: BLOCKER | D3: CASH_USD | E3: Difference -1250000.00
A4: C06 | B4: Duplicate holding row | C4: BLOCKER | D4: EQ003 | E4: 2 rows
A5: C01 | B5: Price move over 25% | C5: WARNING | D5: EQ004 | E5: Move 38.0%
A6: C02 | B6: Stale price (unchanged) | C6: WARNING | D6: FI001 | E6: Price 98.5310 same as last month
A7: C03 | B7: Stale price (unchanged) | C7: WARNING | D7: FI001 | E7: Price 98.5310 same as last month
A8: C06 | B8: Stale price (unchanged) | C8: WARNING | D8: FI001 | E8: Price 98.5310 same as last month
